[
{
  "latency": {
    "avg": 5.70578231292517,
    "min": 2,
    "med": 5,
    "max": 216,
    "p90": 7,
    "p95": 8
  },
  "vus": 1,
  "vus_max": 1
},
{
  "latency": {
    "avg": 7.268676695563488,
    "min": 2,
    "med": 6,
    "max": 224,
    "p90": 8,
    "p95": 9
  },
  "vus": 50,
  "vus_max": 50
},
{
  "latency": {
    "avg": 11.354239839438033,
    "min": 2,
    "med": 6,
    "max": 853,
    "p90": 9,
    "p95": 12
  },
  "vus": 100,
  "vus_max": 100
},
{
  "latency": {
    "avg": 16.923429853181077,
    "min": 2,
    "med": 7,
    "max": 654,
    "p90": 11,
    "p95": 21
  },
  "vus": 150,
  "vus_max": 150
},
{
  "latency": {
    "avg": 18.544151949350216,
    "min": 2,
    "med": 7,
    "max": 1721,
    "p90": 11,
    "p95": 28
  },
  "vus": 1,
  "vus_max": 200
},
{
  "latency": {
    "avg": 22.437391343110598,
    "min": 2,
    "med": 7,
    "max": 867,
    "p90": 13,
    "p95": 218
  },
  "vus": 250,
  "vus_max": 250
},
{
  "latency": {
    "avg": 23.3141592920354,
    "min": 2,
    "med": 7,
    "max": 1701,
    "p90": 12,
    "p95": 217
  },
  "vus": 17,
  "vus_max": 300
},
{
  "latency": {
    "avg": 37.349653863331845,
    "min": 2,
    "med": 8,
    "max": 2087,
    "p90": 216,
    "p95": 230
  },
  "vus": 1,
  "vus_max": 350
},
{
  "latency": {
    "avg": 30.3793259050991,
    "min": 2,
    "med": 7,
    "max": 3166,
    "p90": 25,
    "p95": 220
  },
  "vus": 32,
  "vus_max": 500
}]
